{
  "main": {
    "id": "87b3aee144657469",
    "type": "split",
    "children": [
      {
        "id": "420c1e29223acd00",
        "type": "tabs",
        "children": [
          {
            "id": "4f87cfb238124436",
            "type": "leaf",
            "state": {
              "type": "canvas",
              "state": {
                "file": "Untitled.canvas",
                "viewState": {
                  "x": 0,
                  "y": 0,
                  "zoom": 0
                }
              }
            }
          }
        ]
      }
    ],
    "direction": "vertical"
  },
  "left": {
    "id": "3025bb5a2b152c67",
    "type": "split",
    "children": [
      {
        "id": "827c0f7594470827",
        "type": "tabs",
        "children": [
          {
            "id": "765fe23194a0820b",
            "type": "leaf",
            "state": {
              "type": "file-explorer",
              "state": {
                "sortOrder": "alphabetical"
              }
            }
          },
          {
            "id": "04577764fd6e1eef",
            "type": "leaf",
            "state": {
              "type": "search",
              "state": {
                "query": "",
                "matchingCase": false,
                "explainSearch": false,
                "collapseAll": false,
                "extraContext": false,
                "sortOrder": "alphabetical"
              }
            }
          },
          {
            "id": "63b0d4978569d8f3",
            "type": "leaf",
            "state": {
              "type": "bookmarks",
              "state": {}
            }
          }
        ]
      }
    ],
    "direction": "horizontal",
    "width": 300
  },
  "right": {
    "id": "79944d5ecf4b697a",
    "type": "split",
    "children": [
      {
        "id": "e94447325ccc75a3",
        "type": "tabs",
        "children": [
          {
            "id": "876ba0af0972de68",
            "type": "leaf",
            "state": {
              "type": "backlink",
              "state": {
                "file": "Untitled.canvas",
                "collapseAll": false,
                "extraContext": false,
                "sortOrder": "alphabetical",
                "showSearch": false,
                "searchQuery": "",
                "backlinkCollapsed": false,
                "unlinkedCollapsed": true
              }
            }
          },
          {
            "id": "14e19b8e29594f63",
            "type": "leaf",
            "state": {
              "type": "outgoing-link",
              "state": {
                "file": "Untitled.canvas",
                "linksCollapsed": false,
                "unlinkedCollapsed": true
              }
            }
          },
          {
            "id": "d8b4981dc2a82f12",
            "type": "leaf",
            "state": {
              "type": "tag",
              "state": {
                "sortOrder": "frequency",
                "useHierarchy": true
              }
            }
          },
          {
            "id": "6b4f7b37037bd68f",
            "type": "leaf",
            "state": {
              "type": "outline",
              "state": {
                "file": "Untitled.canvas"
              }
            }
          }
        ]
      }
    ],
    "direction": "horizontal",
    "width": 300
  },
  "left-ribbon": {
    "hiddenItems": {
      "switcher:Open quick switcher": false,
      "graph:Open graph view": false,
      "canvas:Create new canvas": false,
      "daily-notes:Open today's daily note": false,
      "templates:Insert template": false,
      "command-palette:Open command palette": false
    }
  },
  "active": "765fe23194a0820b",
  "lastOpenFiles": [
    "2023-10-31.md",
    "Untitled.canvas",
    "Algoritmi di sorting.md",
    "Array.md",
    "Funzioni  e Dichiarazioni.md",
    "Pasted image 20230926100339.png"
  ]
}